{
	"variables": [],
	"info": {
		"name": "TestArtistaBlog",
		"_postman_id": "40c90ee6-8f91-f502-ce4e-a9146d25c649",
		"description": "",
		"schema": "https://schema.getpostman.com/json/collection/v2.0.0/collection.json"
	},
	"item": [
		{
			"name": "TestGet(ALL)",
			"event": [
				{
					"listen": "test",
					"script": {
						"type": "text/javascript",
						"exec": [
							"tests[\"Exito\"]=responseCode.code==200;"
						]
					}
				}
			],
			"request": {
				"url": "http://localhost:8080/galeriaarte-web/api/artistas/1/blogs",
				"method": "GET",
				"header": [
					{
						"key": "Content-Type",
						"value": "application/json",
						"description": ""
					}
				],
				"body": {
					"mode": "raw",
					"raw": ""
				},
				"description": ""
			},
			"response": []
		},
		{
			"name": "TestPost(LEER DESCRIPCION)",
			"event": [
				{
					"listen": "test",
					"script": {
						"type": "text/javascript",
						"exec": [
							"tests[\"Exito\"]=responseCode.code==200;"
						]
					}
				}
			],
			"request": {
				"url": "http://localhost:8080/galeriaarte-web/api/artistas/1/blogs",
				"method": "POST",
				"header": [
					{
						"key": "Content-Type",
						"value": "application/json",
						"description": ""
					}
				],
				"body": {
					"mode": "raw",
					"raw": " {\n        \"type\": \"blogDetailDTO\",\n        \"contenido\": \"Contenido1\",\n        \"id\": 6, \"name\" :\"c\"\n      \n    }"
				},
				"description": "SI NO FUNCIONA PRESIONAR VARIAS VECES EL BOTON DE SEND HASTA QUE FUNCIONE HASTA QUE SIRVA"
			},
			"response": []
		},
		{
			"name": "TestPut",
			"event": [
				{
					"listen": "test",
					"script": {
						"type": "text/javascript",
						"exec": [
							"tests[\"Exito\"]=responseCode.code==200;"
						]
					}
				}
			],
			"request": {
				"url": "http://localhost:8080/galeriaarte-web/api/artistas/1/blogs/1",
				"method": "PUT",
				"header": [
					{
						"key": "Content-Type",
						"value": "application/json",
						"description": ""
					}
				],
				"body": {
					"mode": "raw",
					"raw": "{\n        \"type\": \"blogDetailDTO\",\n        \"contenido\": \"ContenidoX\",\n        \"id\": 1,\n        \"artista\": {\n            \"id\": 1,\n            \"name\": \"Pedro\"\n        }\n    }"
				},
				"description": ""
			},
			"response": []
		},
		{
			"name": "TestDelete",
			"event": [
				{
					"listen": "test",
					"script": {
						"type": "text/javascript",
						"exec": [
							"tests[\"Exito\"]=responseCode.code==204;"
						]
					}
				}
			],
			"request": {
				"url": "http://localhost:8080/galeriaarte-web/api/artistas/1/blogs/1",
				"method": "DELETE",
				"header": [
					{
						"key": "Content-Type",
						"value": "application/json",
						"description": ""
					}
				],
				"body": {
					"mode": "raw",
					"raw": ""
				},
				"description": ""
			},
			"response": []
		},
		{
			"name": "TestGet",
			"event": [
				{
					"listen": "test",
					"script": {
						"type": "text/javascript",
						"exec": [
							"tests[\"Exito\"]=responseCode.code==200;"
						]
					}
				}
			],
			"request": {
				"url": "http://localhost:8080/galeriaarte-web/api/artistas/2/blogs/2",
				"method": "GET",
				"header": [
					{
						"key": "Content-Type",
						"value": "application/json",
						"description": ""
					}
				],
				"body": {
					"mode": "raw",
					"raw": ""
				},
				"description": ""
			},
			"response": []
		}
	]
}